mailer/TextMessage.py
mailer/__init__.py
mailer/messageable.py
mobile/__init__.py
mobile/atnt.py
mobile/email.py
mobile/phone_number.py
mobile/sprint.py
mobile/tmobile.py
mobile/verizon.py
mobile/virgin_mobile.py
providers/Office365.py
providers/__init__.py
providers/aol.py
providers/comcast.py
providers/email_credentials.py
providers/gmail.py
providers/hotmail.py
providers/live.py
providers/provider.py
providers/yahoo.py
textmail-1.0.data/scripts/textmail
textmail-1.0.dist-info/LICENSE
textmail-1.0.dist-info/METADATA
textmail-1.0.dist-info/WHEEL
textmail-1.0.dist-info/top_level.txt
textmail-1.0.dist-info/RECORD
