Metadata-Version: 2.1
Name: textmail
Version: 1.0
Summary: A tool for sending text messages via email
Home-page: https://github.com/AndrewCPU/textmail
Author: Andrew Stein
Author-email: stein.andrew.01@gmail.com
Classifier: Programming Language :: Python :: 3
Classifier: License :: OSI Approved :: MIT License
Classifier: Operating System :: OS Independent
License-File: LICENSE
